Metadata-Version: 1.1
Name: oauth-slave-accounts
Version: 0.1.1
Summary: Custom Django Oauth backend for Ressource Servers to download full user data fom Authorization Server
Home-page: UNKNOWN
Author: Jean Ribes
Author-email: jean@ribes.me
License: BSD License
Platform: UNKNOWN
Classifier: Environment :: Web Environment
Classifier: Framework :: Django
Classifier: Intended Audience :: Developers
Classifier: Operating System :: OS Independent
Classifier: Programming Language :: Python
Classifier: Programming Language :: Python :: 3.5
Classifier: Programming Language :: Python :: 3.6
Classifier: Topic :: Internet :: WWW/HTTP
Classifier: Topic :: Internet :: WWW/HTTP :: Dynamic Content
